setup.py
varblez1_stage_a/__init__.py
varblez1_stage_a/pdf_exporter.py
varblez1_stage_a.egg-info/PKG-INFO
varblez1_stage_a.egg-info/SOURCES.txt
varblez1_stage_a.egg-info/dependency_links.txt
varblez1_stage_a.egg-info/top_level.txt