Metadata-Version: 1.0
Name: varblez1-stage-a
Version: 1.0
Summary: whatever
Home-page: https://github.com/varblez
Author: zv
Author-email: zack.varble@gmail.com
License: dont
Platform: UNKNOWN
